jhub_shibboleth_user_authenticator/__init__.py
jhub_shibboleth_user_authenticator/shibboleth_user_auth.py
jhub_shibboleth_user_authenticator-0.1.6.data/data/share/jupyterhub/templates/login_shibboleth.html
jhub_shibboleth_user_authenticator-0.1.6.data/data/share/jupyterhub/templates/logout_shibboleth.html
jhub_shibboleth_user_authenticator-0.1.6.dist-info/LICENSE
jhub_shibboleth_user_authenticator-0.1.6.dist-info/METADATA
jhub_shibboleth_user_authenticator-0.1.6.dist-info/WHEEL
jhub_shibboleth_user_authenticator-0.1.6.dist-info/top_level.txt
jhub_shibboleth_user_authenticator-0.1.6.dist-info/RECORD
