Metadata-Version: 2.1
Name: jhub-shibboleth-user-authenticator
Version: 0.1.6
Summary: REMOTE_USER Authenticator (Shibboleth variant): An Authenticator for Jupyterhub to read user information from HTTP request headers, as when running behind an authenticating proxy.
Home-page: https://github.com/ocordes/jhub_shibboleth_user_authenticator
Author: Oliver Cordes (https://github.com/ocordes)
Author-email: ocordes@astro.uni-bonn.de
License: GPLv3
Keywords: Interactive,Interpreter,Shell,Web
Platform: Linux
Platform: Mac OS X
Classifier: Intended Audience :: Developers
Classifier: Intended Audience :: System Administrators
Classifier: Intended Audience :: Science/Research
Classifier: License :: OSI Approved :: GNU General Public License v3 (GPLv3)
Classifier: Programming Language :: Python
Classifier: Programming Language :: Python :: 3
License-File: LICENSE
Requires-Dist: jupyterhub
